{
  "Invalid Params!": "Parámetros inválidos",
  "dni is required": "Debe ingresar su DNI",
  "phone is required": "Debe ingresar su Teléfono",
  "invalid phone": "Formato de teléfono no válido",
  "name is required": "Debe ingresar su Nombre",
  "email is required": "Debe ingresar su Email",
  "invalid email": "Formato de email no válido",
  "value is required": "Debe ingresar el valor",
  "invalid value": "Valor debe ser un número positivo",
  "CastError: Cast to Number failed for value \"NaN\" at path \"phone\"": "Formato de teléfono no válido",
  "CastError: Cast to Number failed for value \"NaN\" at path \"value\"": "Valor debe ser un número positivo",
  "dni already exist": "El DNI ya se encuentra registrado",
  "phone already exist": "El teléfono ya se encuentra registrado",
  "email already exist": "El email ya se encuentra registrado",
  "client created successfully": "Cliente creado exitosamente",
  "Client does not exist": "Cliente no registrado",
  "Wallet is recharged": "Wallet recargada exitosamente",
  "Insufficient balance": "Saldo insuficiente. Por favor recargue primero",
  "Token Denied": "Token denegado. Debe generar una nueva orden de compra",
  "Confirmed Token, Payment Approved": "Pago procesado correctamente",
  "Your Authorization Token has been sent to: ": "Su token de authorización fue enviado a: ",
  "Internal error": "Error",
  "Path `session` is required.": "No se recibió el token de session"
}